hbase/__init__.py
hbase/client.py
hbase/errors.py
hbase/models/__init__.py
hbase/models/cell_set.py
hbase/models/namespaces.py
hbase/models/storage_cluster_status.py
hbase/models/table_info.py
hbase/models/table_list.py
hbase/models/table_schema.py
hbase/models/version.py
hbase/utils.py
hbase-1.0.0.dist-info/LICENSE
hbase-1.0.0.dist-info/WHEEL
hbase-1.0.0.dist-info/METADATA
hbase-1.0.0.dist-info/RECORD
