Metadata-Version: 2.1
Name: hbase
Version: 1.0.0
Summary: Hbase REST API client built using uplink
Home-page: https://github.com/CapgeminiInventIDE/hbase
License: MIT
Keywords: hbase,rest,api
Author: Andy Challis
Author-email: andrewchallis@hotmail.co.uk
Requires-Python: >=3.6.1,<4.0
Classifier: License :: OSI Approved :: MIT License
Classifier: License :: OSI Approved :: Mozilla Public License 2.0 (MPL 2.0)
Classifier: Operating System :: OS Independent
Classifier: Programming Language :: Python :: 3
Classifier: Programming Language :: Python :: 3.7
Classifier: Programming Language :: Python :: 3.8
Classifier: Programming Language :: Python :: 3.9
Requires-Dist: pydantic (>=1.8.2)
Requires-Dist: uplink (>=0.9.4)
Project-URL: Documentation, https://github.com/CapgeminiInventIDE/hbase
Project-URL: Repository, https://github.com/CapgeminiInventIDE/hbase
